{"map":[[{"traits":{"ENDURANCE":{"left":1,"right":1},"SPEED":{"left":1,"right":1},"COMBAT":{"left":1,"right":1},"CAMO":{"left":1,"right":1},"VISION":{"left":1,"right":1}},"acted":false,"actionCost":4,"health":30,"maxHealth":60,"size":"MEDIUM","myStateContext":{"myState":{}},"age":0,"prototype":"PLANT","templateUuid":"3cd05d0f-3096-4cff-9f3b-fc0cd152d73e","uuid":"349047e6-41f7-4c02-ad73-5d808be924d0"},null,null],[null,{"traits":{"ENDURANCE":{"left":1,"right":1},"SPEED":{"left":1,"right":1},"COMBAT":{"left":1,"right":1},"CAMO":{"left":1,"right":1},"VISION":{"left":1,"right":1}},"acted":false,"actionCost":2,"health":15,"maxHealth":30,"size":"SMALL","myStateContext":{"myState":{}},"age":0,"prototype":"PREY","templateUuid":"384258e8-afec-4f18-bce4-b6965e4607b6","uuid":"736fe734-5c7a-4291-b4ca-6f5b54cccb5a"},null],[null,null,{"traits":{"ENDURANCE":{"left":1,"right":1},"SPEED":{"left":1,"right":1},"COMBAT":{"left":1,"right":1},"CAMO":{"left":1,"right":1},"VISION":{"left":1,"right":1}},"acted":false,"actionCost":6,"health":45,"maxHealth":90,"size":"LARGE","myStateContext":{"myState":{}},"age":0,"prototype":"PREDATOR","templateUuid":"4414ba65-0626-4c40-bbb8-691ecd96490c","uuid":"0deeca59-766f-4c68-a5c7-036583d8aa2c"}]],"sizeX":3,"sizeY":3,"turns":1,"currentTurn":0,"currentPos":{"left":0,"right":0},"isNext":false}